{
    "ACTIVE_PARTICIPANT": {
        "selected": {
            "roles": [
                {
                    "title" : "CX User",
                    "description": "CX User wird neu hinzugefügt. Die Rolle ist die Standard Rolle für Users ohne erhöhten Zugriffbedarf. Benutzer können auf Apps & Dienstleistungen zugreifen und das Netzwerk erkunden (Marktplätze, etc.)."
                },
                {
                    "title" : "Purchaser",
                    "description": "Purchaser wird neu hinzugefügt. Die Rolle hat normalen Zugriff auf das Portal mit dem zusätzlichen Recht, Dienste und Apps auf dem Marktplatz zu abonnieren."
                }
            ]
        },
        "deselected": {
            "roles": [
                {
                    "title" : "CX User",
                    "description": "CX User wird entfeernt. Die Rolle ist die Standard Rolle für Users ohne erhöhten Zugriffbedarf. Benutzer können auf Apps & Dienstleistungen zugreifen und das Netzwerk erkunden (Marktplätze, etc.)."
                },
                {
                    "title" : "Purchaser",
                    "description": "Purchaser wird entfeernt. Die Rolle hat normalen Zugriff auf das Portal mit dem zusätzlichen Recht, Dienste und Apps auf dem Marktplatz zu abonnieren."
                }
            ]
        }
    },
    "APP_PROVIDER": {
        "selected": {
            "roles": [
                {
                    "title" : "App Manager",
                    "description": "App Manager wird neu hinzugefügt. Der App Manager ist in der Lage, neue App-Einträge für den Marktplatz hinzuzufügen und Abonnementanfragen zu verwalten. Auch der App-Änderungsprozess kann vom App Manager verwaltet werden."
                },
                {
                    "title" : "App Developer",
                    "description": "App Developer wird neu hinzugefügt. Der App Developer kann eine für die App-Auflistung erstellte App ändern."
                },
                {
                    "title" : "Sales Manager",
                    "description": "Sales Manager wird neu hinzugefügt. Der Sales Manager kann Abonnementanfragen einsehen, verwalten und aktivieren."
                }
            ],
            "features": [
                {
                    "title" : "App Management",
                    "description": "Das App-Management-Board bietet dem App-Manager/Entwickler und dem Vertriebsleiter einen Überblick über die eigenen Apps. Apps können geändert/gewartet und neue App-Releases gestartet werden.",
                    "details": "link to the functional explanation"
                },
                {
                    "title" : "App Release Process",
                    "description": "Überblick über die Schritte des App-Release-Prozesses und ermöglicht das generieren einer neuen App-Release-Anfrage für den CX Marktplatz.",
                    "details": "link to the functional explanation"
                },
                {
                    "title" : "App Subscription Management",
                    "description": "Verwaltung von App-Abonnementanfragen; Übersicht über Aktivierung und verbundene Dienste.",
                    "details": "link to the functional explanation"
                }
            ]
        },
        "deselected": {
            "roles": [
                {
                    "title" : "App Manager",
                    "description": "App Manager wird entfeernt. Der App Manager ist in der Lage, neue App-Einträge für den Marktplatz hinzuzufügen und Abonnementanfragen zu verwalten. Auch der App-Änderungsprozess kann vom App Manager verwaltet werden."
                },
                {
                    "title" : "App Developer",
                    "description": "App Developer wird entfeernt. Der App Developer kann eine für die App-Auflistung erstellte App ändern."
                },
                {
                    "title" : "Sales Manager",
                    "description": "Sales Manager wird entfeernt. Der Sales Manager kann Abonnementanfragen einsehen, verwalten und aktivieren."
                }
            ],
            "features": [
                {
                    "title" : "App Management",
                    "description": "Das App-Management-Board bietet dem App-Manager/Entwickler und dem Vertriebsleiter einen Überblick über die eigenen Apps. Apps können geändert/gewartet und neue App-Releases gestartet werden.",
                    "details": "link to the functional explanation"
                },
                {
                    "title" : "App Release Process",
                    "description": "Überblick über die Schritte des App-Release-Prozesses und ermöglicht das generieren einer neuen App-Release-Anfrage für den CX Marktplatz",
                    "details": "link to the functional explanation"
                },
                {
                    "title" : "App Subscription Management",
                    "description": "Verwaltung von App-Abonnementanfragen; Übersicht über Aktivierung und verbundene Dienste.",
                    "details": "link to the functional explanation"
                }
            ]
        }
    },
    "SERVICE_PROVIDER": {
        "selected": {
            "roles": [
                {
                    "title" : "Service Manager",
                    "description": "Service Manager wird neu hinzugefügt. Der Service Manager ist in der Lage, neue Service-Einträge für den Marktplatz hinzuzufügen und Abonnementanfragen zu verwalten. Auch der Service-Änderungsprozess kann vom Service Manager verwaltet werden."
                },
                {
                    "title" : "Sales Manager",
                    "description": "Sales Manager wird neu hinzugefügt. Der Sales Manager kann Abonnementanfragen einsehen, verwalten und aktivieren."
                }
            ],
            "features": [
                {
                    "title" : "Service Management",
                    "description": "Das Service Management Board bietet dem Service Manager und dem Vertriebsleiter einen Überblick über die eigenen Services. Services können geändert/gepflegt und neue Service-Releases gestartet werden.",
                    "details": "link to the functional explanation"
                },
                {
                    "title" : "Service Release Process",
                    "description": "Überblick über die Schritte des Service-Release-Prozesses und ermöglicht das generieren einer neuen Service-Release-Anfrage für den CX Marktplatz.",
                    "details": "link to the functional explanation"
                },
                {
                    "title" : "Service Subscription Management",
                    "description": "Verwaltung von Dienstabonnementanfragen; Übersicht über Aktivierung und verbundene Dienste.",
                    "details": "link to the functional explanation"
                }
            ]
        },
        "deselected": {
            "roles": [
                {
                    "title" : "Service Manager",
                    "description": "Service Manager wird entfeernt. Der Service Manager wird neu hinzugefügt. Der Service Manager ist in der Lage, neue Service-Einträge für den Marktplatz hinzuzufügen und Abonnementanfragen zu verwalten. Auch der Service-Änderungsprozess kann vom Service Manager verwaltet werden."
                },
                {
                    "title" : "Sales Manager",
                    "description": "Sales Manager wird entfeernt. Der Sales Manager kann Abonnementanfragen einsehen, verwalten und aktivieren."
                }
            ],
            "features": [
                {
                    "title" : "Service Management",
                    "description": "Das Service Management Board bietet dem Service Manager und dem Vertriebsleiter einen Überblick über die eigenen Services. Services können geändert/gepflegt und neue Service-Releases gestartet werden.",
                    "details": "link to the functional explanation"
                },
                {
                    "title" : "Service Release Process",
                    "description": "Überblick über die Schritte des Service-Release-Prozesses und ermöglicht das generieren einer neuen Service-Release-Anfrage für den CX Marktplatz.",
                    "details": "link to the functional explanation"
                },
                {
                    "title" : "Service Subscription Management",
                    "description": "Verwaltung von Dienstabonnementanfragen; Übersicht über Aktivierung und verbundene Dienste.",
                    "details": "link to the functional explanation"
                }
            ]
        }
    }
}
